README.rst
setup.py
pipi/__init__.py
pipi.egg-info/PKG-INFO
pipi.egg-info/SOURCES.txt
pipi.egg-info/dependency_links.txt
pipi.egg-info/entry_points.txt
pipi.egg-info/top_level.txt